fa/VERSION
fa/__init__.py
fa/audio/__init__.py
fa/audio/audio.py
fa/conf/BR.conf
fa/conf/SR.conf
fa/conf/TEST.conf
fa/conf/TS.conf
fa/falib/__init__.py
fa/falib/config.py
fa/falib/falib.py
fa/viewer/__init__.py
fa/viewer/buffer.py
fa/viewer/fa_viewer.py
fa/viewer/modes.py
fa/viewer/viewer.ui
fa_archiver-1.0.0.dist-info/LICENSE
fa_archiver-1.0.0.dist-info/METADATA
fa_archiver-1.0.0.dist-info/WHEEL
fa_archiver-1.0.0.dist-info/entry_points.txt
fa_archiver-1.0.0.dist-info/top_level.txt
fa_archiver-1.0.0.dist-info/RECORD
